check_msdefender-1.2.2.dist-info/METADATA
check_msdefender-1.2.2.dist-info/WHEEL
check_msdefender-1.2.2.dist-info/entry_points.txt
check_msdefender-1.2.2.dist-info/licenses/LICENSE
check_msdefender/__init__.py
check_msdefender/__main__.py
check_msdefender/check_msdefender.py
check_msdefender/cli/__init__.py
check_msdefender/cli/__main__.py
check_msdefender/cli/commands/__init__.py
check_msdefender/cli/commands/alerts.py
check_msdefender/cli/commands/detail.py
check_msdefender/cli/commands/lastseen.py
check_msdefender/cli/commands/machines.py
check_msdefender/cli/commands/onboarding.py
check_msdefender/cli/commands/products.py
check_msdefender/cli/commands/vulnerabilities.py
check_msdefender/cli/decorators.py
check_msdefender/cli/handlers.py
check_msdefender/core/__init__.py
check_msdefender/core/auth.py
check_msdefender/core/config.py
check_msdefender/core/defender.py
check_msdefender/core/exceptions.py
check_msdefender/core/logging_config.py
check_msdefender/core/nagios.py
check_msdefender/integration.py
check_msdefender/services/__init__.py
check_msdefender/services/alerts_service.py
check_msdefender/services/detail_service.py
check_msdefender/services/lastseen_service.py
check_msdefender/services/machines_service.py
check_msdefender/services/models.py
check_msdefender/services/onboarding_service.py
check_msdefender/services/products_service.py
check_msdefender/services/vulnerabilities_service.py
check_msdefender-1.2.2.dist-info/RECORD
