Metadata-Version: 2.1
Name: check-msdefender
Version: 1.2.2
Summary: A Nagios plugin for monitoring Microsoft Defender API endpoints
Keywords: nagios,monitoring,microsoft,graph,api,azure
Author-Email: ldvchosal <ldvchosal@github.com>
License: MIT
Classifier: Development Status :: 5 - Production/Stable
Classifier: Intended Audience :: System Administrators
Classifier: License :: OSI Approved :: MIT License
Classifier: Operating System :: OS Independent
Classifier: Programming Language :: Python :: 3
Classifier: Programming Language :: Python :: 3.10
Classifier: Programming Language :: Python :: 3.11
Classifier: Programming Language :: Python :: 3.12
Classifier: Programming Language :: Python :: 3.13
Classifier: Topic :: System :: Monitoring
Classifier: Topic :: System :: Systems Administration
Project-URL: Homepage, https://github.com/lduchosal/check_msdefender
Project-URL: Bug Reports, https://github.com/lduchosal/check_msdefender/issues
Project-URL: Source, https://github.com/lduchosal/check_msdefender
Project-URL: Documentation, https://github.com/lduchosal/check_msdefender/blob/main/README.md
Requires-Python: >=3.10
Requires-Dist: nagiosplugin>=1.4.0
Requires-Dist: azure-identity>=1.12.0
Requires-Dist: click<9.0,>=8.0
